pylibsparseir-0.8.0.dist-info/RECORD
pylibsparseir-0.8.0.dist-info/WHEEL
pylibsparseir-0.8.0.dist-info/METADATA
pylibsparseir-0.8.0.dist-info/licenses/LICENSE
pylibsparseir/ctypes_wrapper.py
pylibsparseir/sparseir.h
pylibsparseir/clean_build_artifacts.py
pylibsparseir/constants.py
pylibsparseir/ctypes_autogen.py
pylibsparseir/__init__.py
pylibsparseir/core.py
pylibsparseir/libsparse_ir_capi.dylib
