Metadata-Version: 2.4
Name: pylibsparseir
Version: 0.8.0
Summary: Python bindings for the sparse-ir-capi library
Project-URL: Homepage, https://github.com/SpM-lab/sparse-ir-rs
Project-URL: Documentation, https://github.com/SpM-lab/sparse-ir-rs
Project-URL: Repository, https://github.com/SpM-lab/sparse-ir-rs
Project-URL: Issues, https://github.com/SpM-lab/sparse-ir-rs/issues
Maintainer: SpM-lab
License: MIT License
License-File: LICENSE
Classifier: Development Status :: 4 - Beta
Classifier: Intended Audience :: Developers
Classifier: Intended Audience :: Science/Research
Classifier: License :: OSI Approved :: MIT License
Classifier: Operating System :: OS Independent
Classifier: Programming Language :: Python :: 3
Classifier: Programming Language :: Python :: 3.10
Classifier: Programming Language :: Python :: 3.11
Classifier: Programming Language :: Python :: 3.12
Classifier: Programming Language :: Rust
Classifier: Topic :: Scientific/Engineering :: Physics
Requires-Python: >=3.10
Requires-Dist: numpy>=1.26.4
Requires-Dist: scipy
